tests
cloudshell
