Metadata-Version: 1.0
Name: cloudshell-tg-teravm
Version: 1.0.2
Summary: QualiSystems Python package
Home-page: https://github.com/QualiSystems/cloudshell-tg-teravm
Author: QualiSystems
Author-email: info@qualisystems.com
License: UNKNOWN
Platform: UNKNOWN
